failure/__init__.py
failure/_utils.py
failure/failure.py
failure/finders.py
failure/tests/__init__.py
failure/tests/test_failure.py
failure/tests/test_finders.py
failure/tests/test_utils.py
failure-1.0.1.dist-info/DESCRIPTION.rst
failure-1.0.1.dist-info/METADATA
failure-1.0.1.dist-info/RECORD
failure-1.0.1.dist-info/WHEEL
failure-1.0.1.dist-info/metadata.json
failure-1.0.1.dist-info/pbr.json
failure-1.0.1.dist-info/top_level.txt
